mcorr/__init__.py
mcorr/cli.py
mcorr/fit.py
mcorr-20180314.dist-info/DESCRIPTION.rst
mcorr-20180314.dist-info/METADATA
mcorr-20180314.dist-info/RECORD
mcorr-20180314.dist-info/WHEEL
mcorr-20180314.dist-info/entry_points.txt
mcorr-20180314.dist-info/metadata.json
mcorr-20180314.dist-info/top_level.txt
