Metadata-Version: 2.0
Name: mcorr
Version: 20180314
Summary: Inferring recombination rates from correlation profiles
Home-page: https://github.com/kussell-lab/mcorr
Author: Mingzhi Lin
Author-email: mingzhi9@gmail.com
License: MIT
Platform: UNKNOWN
Requires-Python: >=3
Requires-Dist: numpy
Requires-Dist: matplotlib
Requires-Dist: lmfit
Requires-Dist: tqdm
